[
    {
        "en": "bring up (sb)",
        "ja": "～を育てる"
    },
    {
        "en": "come up",
        "ja": "(話が)出る"
    },
    {
        "en": "eat up (sth)",
        "ja": "～を食べつくす"
    },
    {
        "en": "get up",
        "ja": "起きる"
    },
    {
        "en": "give up (sth)",
        "ja": "～を諦める"
    },
    {
        "en": "look up (sth)",
        "ja": "～を調べる"
    },
    {
        "en": "make up",
        "ja": "仲直りする"
    },
    {
        "en": "make up (sth)",
        "ja": "～を構成する"
    },
    {
        "en": "make up for (sth)",
        "ja": "～を埋め合わせる"
    },
    {
        "en": "pick up (sth)",
        "ja": "～を拾い上げる"
    },
    {
        "en": "put up with (sth)",
        "ja": "～を我慢する"
    },
    {
        "en": "set up (sth)",
        "ja": "～を設置する、準備する"
    },
    {
        "en": "show up",
        "ja": "現れる"
    },
    {
        "en": "speed up",
        "ja": "スピードを上げる"
    },
    {
        "en": "stand up",
        "ja": "立つ"
    },
    {
        "en": "stay up",
        "ja": "夜更かしする"
    },
    {
        "en": "take up (sth)",
        "ja": "～を新しく始める"
    },
    {
        "en": "turn up",
        "ja": "(人が)やってくる、(物が)見つかる"
    },
    {
        "en": "turn up (sth)",
        "ja": "(音量など)を上げる"
    },
    {
        "en": "wake up",
        "ja": "目を覚ます"
    },
    {
        "en": "",
        "ja": ""
    },
    {
        "en": "",
        "ja": ""
    }
]