[
    {
        "category": "同意・賛成",
        "en": "Absolutely.",
        "ja": "まったくその通り。"
    },
    {
        "category": "同意・賛成",
        "en": "Exactly.",
        "ja": "まさに。"
    },
    {
        "category": "同意・賛成",
        "en": "For sure.",
        "ja": "絶対そう。"
    },
    {
        "category": "同意・賛成",
        "en": "I don't see why not.",
        "ja": "問題ないと思うよ。"
    },
    {
        "category": "同意・賛成",
        "en": "I'm with you.",
        "ja": "同感です。"
    },
    {
        "category": "同意・賛成",
        "en": "Totally.",
        "ja": "ほんとにそう。"
    },
    {
        "category": "同意・賛成",
        "en": "True that.",
        "ja": "それな。"
    },
    {
        "category": "同意・賛成",
        "en": "Right.",
        "ja": "そうだね。"
    },





    {
        "category": "共感・理解",
        "en": "Fair enough.",
        "ja": "それも一理あるね。納得したよ。"
    },
    {
        "category": "共感・理解",
        "en": "Gotcha.",
        "ja": "了解、わかったよ。"
    },
    {
        "category": "共感・理解",
        "en": "I get your point.",
        "ja": "言いたいことはわかるよ。"
    },
    {
        "category": "共感・理解",
        "en": "I hear you.",
        "ja": "わかるよ～。"
    },
    {
        "category": "共感・理解",
        "en": "I know how you feel.",
        "ja": "その気持ちわかるよ。"
    },
    {
        "category": "共感・理解",
        "en": "I see.",
        "ja": "なるほど。わかりました。"
    },
    {
        "category": "共感・理解",
        "en": "I see what you mean.",
        "ja": "言いたいことはわかるよ。"
    },
    {
        "category": "共感・理解",
        "en": "I see what you're saying.",
        "ja": "言っていることはわかるよ。"
    },
    {
        "category": "共感・理解",
        "en": "Interesting.",
        "ja": "面白いね。"
    },
    {
        "category": "共感・理解",
        "en": "That makes sense.",
        "ja": "なるほど、納得したよ。"
    },
    {
        "category": "共感・理解",
        "en": "That's a fair point.",
        "ja": "確かにそうだね。"
    },
    {
        "category": "共感・理解",
        "en": "That's true.",
        "ja": "確かにそうだね。"
    },




    {
        "category": "断る",
        "en": "I'd rather not.",
        "ja": "遠慮します。"
    },
    {
        "category": "断る",
        "en": "It's fine.",
        "ja": "けっこうです。"
    },
    {
        "category": "断る",
        "en": "No way!",
        "ja": "嫌だよ！"
    },





    {
        "category": "任せる",
        "en": "Either is fine.",
        "ja": "どっちでもいいよ。"
    },
    {
        "category": "任せる",
        "en": "I'll leave it up to you.",
        "ja": "君に任せるよ。"
    },
    {
        "category": "任せる",
        "en": "It's up to you.",
        "ja": "君次第だよ。任せるよ。"
    },





    {
        "category": "保留",
        "en": "I'll go ask him.",
        "ja": "彼に聞いてくるよ。"
    },
    {
        "category": "保留",
        "en": "I'll let you know later.",
        "ja": "後で伝えるよ。"
    },
    {
        "category": "保留",
        "en": "t depends on the weather.",
        "ja": "お天気によります。"
    },
    {
        "category": "保留",
        "en": "Let me check with my supervisor.",
        "ja": "上司に確認させてください。"
    },




    {
        "category": "褒める",
        "en": "Cool!",
        "ja": "おお、いいね！すごいじゃん！"
    },
    {
        "category": "褒める",
        "en": "Good for you.",
        "ja": "よかったね、おめでとう。"
    },
    {
        "category": "褒める",
        "en": "It couldn't be better.",
        "ja": "これ以上ないくらい最高だ。"
    },
    {
        "category": "褒める",
        "en": "It couldn't have been better.",
        "ja": "これ以上ないくらい最高だったよ。"
    },
    {
        "category": "褒める",
        "en": "What great news!",
        "ja": "素晴らしい知らせだね！"
    },




    {
        "category": "感謝",
        "en": "I'd appreciate it.",
        "ja": "ありがたいです。"
    },
    {
        "category": "感謝",
        "en": "Thanks.",
        "ja": "ありがとう。"
    },
    {
        "category": "感謝",
        "en": "That would be appreciated.",
        "ja": "そうしてもらえるとありがたいです。"
    },
    {
        "category": "感謝",
        "en": "That'll be a great help.",
        "ja": "そうしてもらえるととても助かります。"
    },
    




    
{
        "category": "",
        "en": "It's OK.",
        "ja": "大丈夫だよ。"
    },



    {
        "category": "初耳",
        "en": "Hmm, I didn't know that.",
        "ja": "へぇ～、知らなかった。"
    },
    {
        "category": "初耳",
        "en": "That's news to me.",
        "ja": "それは知らなかったよ。"
    },






    {
        "category": "不明",
        "en": "I'm not sure about that.",
        "ja": "それについてはよくわかりません。"
    },





    





    {
        "category": "許可",
        "en": "Go ahead.",
        "ja": "どうぞ。"
    },





    {
        "category": "引き受ける",
        "en": "I'd be happy to.",
        "ja": "喜んで。"
    },
    {
        "category": "引き受ける",
        "en": "I'd love to.",
        "ja": "喜んで。"
    },





    





    {
        "category": "驚き",
        "en": "Get out of here.",
        "ja": "うそでしょ！信じられない！"
    },
    {
        "category": "驚き",
        "en": "No kidding!",
        "ja": "冗談でしょ！"
    },
    {
        "category": "驚き",
        "en": "Really?",
        "ja": "ほんとに？"
    },
    {
        "category": "驚き",
        "en": "Seriously?",
        "ja": "まじで？"
    },
    {
        "category": "驚き",
        "en": "That's crazy.",
        "ja": "やばいね。"
    },
    {
        "category": "驚き",
        "en": "That's surprising.",
        "ja": "それは意外だね。"
    },
    {
        "category": "驚き",
        "en": "You're kidding!",
        "ja": "冗談でしょ！"
    }
]